src/ram/ram_dual_port.v
//-----------------------------------------------------
// Design Name : ram_dp_sr_sw
// File Name   : ram_dp_sr_sw.v
// Function    : Synchronous read write RAM
// Coder       : Deepak Kumar Tala
//-----------------------------------------------------
module ram_dp_sr_sw (
	clk       , // Clock Input
	address_0 , // address_0 Input
	data_0    , // data_0 bi-directional
	cs_0      , // Chip Select
	we_0      , // Write Enable/Read Enable
	oe_0      , // Output Enable
	address_1 , // address_1 Input
	data_1    , // data_1 bi-directional
	cs_1      , // Chip Select
	we_1      , // Write Enable/Read Enable
	oe_1        // Output Enable
); 

parameter DATA_0_WIDTH = 8 ;
parameter ADDR_WIDTH = 16 ;
parameter RAM_DEPTH = 256 ; // 1 << ADDR_WIDTH;

//--------------Input Ports----------------------- 
input clk;
input [ADDR_WIDTH-1:0] address_0 ;
input cs_0 ;
input we_0 ;
input oe_0 ; 
input [ADDR_WIDTH-1:0] address_1 ;
input cs_1 ;
input we_1 ;
input oe_1 ; 

//--------------Inout Ports----------------------- 
inout [DATA_0_WIDTH-1:0] data_0 ; 
inout [DATA_0_WIDTH-1:0] data_1 ;

//--------------Internal variables---------------- 
reg [DATA_0_WIDTH-1:0] data_0_out ; 
reg [DATA_0_WIDTH-1:0] data_1_out ;
reg [DATA_0_WIDTH-1:0] mem [0:RAM_DEPTH-1];

//--------------Code Starts Here------------------ 
// Memory Write Block 
// Write Operation : When we_0 = 1, cs_0 = 1
always @ (posedge clk)
begin : MEM_WRITE
	if ( cs_0 && we_0 ) begin
		mem[address_0] <= data_0;
	end else if (cs_1 && we_1) begin 
		mem[address_1] <= data_1;
	end
end

// Tri-State Buffer control 
// output : When we_0 = 0, oe_0 = 1, cs_0 = 1
assign data_0 = (cs_0 && oe_0 && !we_0) ? data_0_out : 8'bz; 

// Memory Read Block 
// Read Operation : When we_0 = 0, oe_0 = 1, cs_0 = 1
always @ (posedge clk)
begin : MEM_READ_0
	if (cs_0 && !we_0 && oe_0) begin
		data_0_out <= mem[address_0]; 
	end else begin
		data_0_out <= 0; 
	end  
end 

//Second Port of RAM
// Tri-State Buffer control 
// output : When we_0 = 0, oe_0 = 1, cs_0 = 1
assign data_1 = (cs_1 && oe_1 && !we_1) ? data_1_out : 8'bz; 

// Memory Read Block 1 
// Read Operation : When we_1 = 0, oe_1 = 1, cs_1 = 1
always @ (posedge clk)
begin : MEM_READ_1
	if (cs_1 && !we_1 && oe_1) begin
		data_1_out <= mem[address_1]; 
	end else begin
		data_1_out <= 0;
	end
end

endmodule // End of Module ram_dp_sr_sw

src/ram/tb_ram_dual_port.v
module tb_ram_dual_port ();
parameter ADDR_WIDTH = 16;
parameter DATA_WIDTH = 8;
parameter DEPTH = 16;

reg clk;

reg cs_0;
reg we_0;
reg oe_0;

reg cs_1;
reg we_1;
reg oe_1;

reg [ADDR_WIDTH-1:0] addr_0;
wire [DATA_WIDTH-1:0] data_0;

reg [ADDR_WIDTH-1:0] addr_1;
wire [DATA_WIDTH-1:0] data_1;

reg [DATA_WIDTH-1:0] tb_data;

integer i;

ram_dp_sr_sw dut ( 
    .clk(clk),
    .address_0(addr_0),
    .data_0(data_0),
    .cs_0(cs_0),
    .we_0(we_0),
    .oe_0(oe_0),
    .address_1(addr_1),
    .data_1(data_1),
    .cs_1(cs_1),
    .we_1(we_1),
    .oe_1(oe_1)
);

always #10 clk = ~clk;
assign data_0 = !oe_0 ? tb_data : 'hz;

initial begin 
    { clk, tb_data} <= 0; 
    { cs_0, we_0, addr_0, oe_0} <= 0; 
    { cs_1, we_1, addr_1, oe_1} <= 0; 

    repeat(2) @(posedge clk);

    $display ("first port");

    for ( i = 0; i < 10; i = i + 1) begin 
        repeat (1) @(posedge clk)  addr_0 <= i; we_0 <= 1; cs_0 <= 1; oe_0 <= 0; tb_data <= $random;
        $display ("ram_dp_inp_data %d %d ", tb_data, data_0);
    end

    $display ("second port");

    for ( i = 0; i < 10; i = i + 1) begin 
        repeat (1) @(posedge clk)  addr_1 <= i; we_1 <= 0; cs_1 <= 1; oe_1 <= 1; 
        $display ("ram_dp_out_data %d", data_1);
    end

    #200 $finish ;
end

initial begin
    $dumpfile("test_ram_dual_port.vcd");
    $dumpvars(0,dut);
    $dumpflush;
end

endmodule

src/ram/test_ram_dual_port.vcd
$date
	Sat Oct 24 22:28:28 2020
$end
$version
	Icarus Verilog
$end
$timescale
	1s
$end
$scope module tb_ram_dual_port $end
$scope module dut $end
$var wire 16 ! address_0 [15:0] $end
$var wire 16 " address_1 [15:0] $end
$var wire 1 # clk $end
$var wire 1 $ cs_0 $end
$var wire 1 % cs_1 $end
$var wire 8 & data_0 [7:0] $end
$var wire 1 ' oe_0 $end
$var wire 1 ( oe_1 $end
$var wire 1 ) we_0 $end
$var wire 1 * we_1 $end
$var wire 8 + data_1 [7:0] $end
$var reg 8 , data_0_out [7:0] $end
$var reg 8 - data_1_out [7:0] $end
$scope begin MEM_READ_0 $end
$upscope $end
$scope begin MEM_READ_1 $end
$upscope $end
$scope begin MEM_WRITE $end
$upscope $end
$upscope $end
$upscope $end
$enddefinitions $end
#0
$dumpvars
bx -
bx ,
bz +
0*
0)
0(
0'
b0 &
0%
0$
0#
b0 "
b0 !
$end
#10
b0 -
b0 ,
1#
#20
0#
#30
1#
#40
0#
#50
b100100 &
1$
1)
1#
#60
0#
#70
b10000001 &
b1 !
1#
#80
0#
#90
b1001 &
b10 !
1#
#100
0#
#110
b1100011 &
b11 !
1#
#120
0#
#130
b1101 &
b100 !
1#
#140
0#
#150
b10001101 &
b101 !
1#
#160
0#
#170
b1100101 &
b110 !
1#
#180
0#
#190
b10010 &
b111 !
1#
#200
0#
#210
b1 &
b1000 !
1#
#220
0#
#230
b1101 &
b1001 !
1#
#240
0#
#250
b0 +
1(
1%
1#
#260
0#
#270
b100100 +
b100100 -
b1 "
1#
#280
0#
#290
b10000001 +
b10000001 -
b10 "
1#
#300
0#
#310
b1001 +
b1001 -
b11 "
1#
#320
0#
#330
b1100011 +
b1100011 -
b100 "
1#
#340
0#
#350
b1101 +
b1101 -
b101 "
1#
#360
0#
#370
b10001101 +
b10001101 -
b110 "
1#
#380
0#
#390
b1100101 +
b1100101 -
b111 "
1#
#400
0#
#410
b10010 +
b10010 -
b1000 "
1#
#420
0#
#430
b1 +
b1 -
b1001 "
1#
#440
0#
#450
b1101 +
b1101 -
1#
