src/epcri/ecpri.v
// test project for revising the verilog

module  fifo ( out_d, out_clk, read_flg, inp_clk, inp_d, write_flg, reset);

input wire reset;
input wire[7:0] inp_d;
input wire inp_clk;
input wire out_clk;
input wire read_flg;
input wire write_flg;
output reg[7:0] out_d;

reg [32:0] buffer[8];

reg [7:0] inp_addr;
reg [7:0] out_addr;

integer j;

always @(posedge reset)
begin
    inp_addr <= 0;
    out_addr <= 0;
    for (j=0; j < 8 ; j=j+1) begin
        buffer[j] <= 8'b0; //reset array
    end
end

always @(posedge inp_clk)
begin
    if (write_flg)
    begin
        buffer[inp_addr] <= inp_d;
        inp_addr <= inp_addr + 1;
    end
end

always @(posedge out_clk) 
begin
    if (read_flg)
    begin
        out_d <= buffer[out_addr];
        out_addr <= out_addr + 1;
    end
end

endmodule

src/fifo/tb_fifo.v
// create test bench
module tb_fifo();

reg reset;
reg [7:0] inp_d;
reg inp_clk;
reg out_clk;
wire [7:0] out_d;

// instance of the module 
fifo dut( .out_d(out_d), .out_clk(inp_clk), .inp_clk(inp_clk), .inp_d(inp_d), .reset(reset));

// provide clock 
initial 
begin 
inp_clk <= 0;
out_clk <= 0;
forever #10 inp_clk =~inp_clk;
forever #10 out_clk =~out_clk;
end

// provide input to the module 
initial 
begin 
#50;
reset <= 0;
#50
inp_d <= 0;
#10;
inp_d <= 8;
#10;
inp_d <= 0;
#50;
$finish;
end

// dump the output 
initial
begin
	$dumpfile("test.vcd");
	$dumpvars(0,inp_d);
	$dumpvars(0,inp_clk);
	$dumpvars(0,out_d);
	$dumpvars(0,out_clk);
	$dumpvars(0,reset);
	$dumpvars(0,dut);
end

endmodule

src/fifo/test.vcd
$date
	Thu Oct  8 23:05:32 2020
$end
$version
	Icarus Verilog
$end
$timescale
	1s
$end
$scope module tb_fifo $end
$var reg 8 ! inp_d [7:0] $end
$upscope $end
$scope module tb_fifo $end
$var reg 1 " inp_clk $end
$upscope $end
$scope module tb_fifo $end
$var wire 8 # out_d [7:0] $end
$upscope $end
$scope module tb_fifo $end
$var reg 1 $ out_clk $end
$upscope $end
$scope module tb_fifo $end
$var reg 1 % reset $end
$upscope $end
$scope module tb_fifo $end
$scope module dut $end
$var wire 1 " inp_clk $end
$var wire 8 & inp_d [7:0] $end
$var wire 1 " out_clk $end
$var wire 1 ' read_flg $end
$var wire 1 % reset $end
$var wire 1 ( write_flg $end
$var reg 8 ) inp_addr [7:0] $end
$var reg 8 * out_addr [7:0] $end
$var reg 8 + out_d [7:0] $end
$var integer 32 , j [31:0] $end
$upscope $end
$upscope $end
$enddefinitions $end
#0
$dumpvars
bx ,
bx +
bx *
bx )
0(
0'
bx &
x%
0$
bx #
0"
bx !
$end
#10
0%
1"
#20
b0 *
b0 )
b1000 ,
1%
0"
#30
1(
1"
#40
b0 !
b0 &
0"
#50
b1 )
1"
#60
b1 !
b1 &
0"
#70
b10 )
1"
#80
b10 !
b10 &
0"
#90
b11 )
1"
#100
b11 !
b11 &
0"
#110
b100 )
1"
#120
0"
#130
b101 )
0(
1"
#140
1'
0"
#150
b1 *
b0 #
b0 +
1"
#160
0"
#170
b10 *
b1 #
b1 +
1"
#180
0"
#190
b11 *
b10 #
b10 +
1"
#200
0"
#210
b100 *
b11 #
b11 +
1"
#220
0"
#230
b101 *
1"
#240
0'
0"
